VERSION
taxamo/__init__.py
taxamo/api.py
taxamo/error.py
taxamo/http_client.py
taxamo/swagger.py
taxamo/data/ca-certificates.crt
taxamo/models/C.py
taxamo/models/N.py
taxamo/models/__init__.py
taxamo/models/additional_currencies.py
taxamo/models/additional_currency.py
taxamo/models/additional_interactions.py
taxamo/models/buyer_tax_number_schema.py
taxamo/models/by_country.py
taxamo/models/by_status.py
taxamo/models/by_taxation_type.py
taxamo/models/calculateSimpleTaxOut.py
taxamo/models/calculateTaxIn.py
taxamo/models/calculateTaxLocationOut.py
taxamo/models/calculateTaxOut.py
taxamo/models/cancelRefundBySubnumberOut.py
taxamo/models/cancelRefundsOut.py
taxamo/models/cancelTransactionOut.py
taxamo/models/captcha.py
taxamo/models/capturePaymentOut.py
taxamo/models/confirmTransactionIn.py
taxamo/models/confirmTransactionOut.py
taxamo/models/control_flags.py
taxamo/models/countries.py
taxamo/models/country.py
taxamo/models/country_schema.py
taxamo/models/createPaymentIn.py
taxamo/models/createPaymentOut.py
taxamo/models/createRefundIn.py
taxamo/models/createRefundOut.py
taxamo/models/createSMSTokenIn.py
taxamo/models/createSMSTokenOut.py
taxamo/models/createTransactionIn.py
taxamo/models/createTransactionOut.py
taxamo/models/currency_schema.py
taxamo/models/custom_fields.py
taxamo/models/emailInvoiceIn.py
taxamo/models/emailInvoiceOut.py
taxamo/models/emailRefundIn.py
taxamo/models/emailRefundOut.py
taxamo/models/evidence.py
taxamo/models/evidence_schema.py
taxamo/models/getCountriesDictOut.py
taxamo/models/getCurrenciesDictOut.py
taxamo/models/getDailySettlementStatsOut.py
taxamo/models/getDetailedRefundsOut.py
taxamo/models/getDomesticSummaryReportOut.py
taxamo/models/getEuViesReportOut.py
taxamo/models/getProductTypesDictOut.py
taxamo/models/getRefundsOut.py
taxamo/models/getSettlementOut.py
taxamo/models/getSettlementStatsByCountryOut.py
taxamo/models/getSettlementStatsByTaxationTypeOut.py
taxamo/models/getSettlementSummaryOut.py
taxamo-0.0.18.dist-info/LICENSE
taxamo-0.0.18.dist-info/LICENSE.txt
taxamo-0.0.18.dist-info/METADATA
taxamo-0.0.18.dist-info/WHEEL
taxamo-0.0.18.dist-info/top_level.txt
taxamo-0.0.18.dist-info/RECORD
