Metadata-Version: 2.1
Name: taxamo
Version: 0.0.18
Summary: Taxamo python bindings
Home-page: https://github.com/taxamo/taxamo-python
Author: Taxamo
Author-email: support@taxamo.com
License: UNKNOWN
Download-URL: https://github.com/taxamo/taxamo-python/tarball/0.0.16
Platform: UNKNOWN
Classifier: Development Status :: 5 - Production/Stable
Classifier: Intended Audience :: Developers
Classifier: License :: OSI Approved :: Apache Software License
Classifier: Operating System :: OS Independent
Classifier: Programming Language :: Python
Classifier: Programming Language :: Python :: 2
Classifier: Programming Language :: Python :: 2.7
Classifier: Programming Language :: Python :: 3
Classifier: Programming Language :: Python :: 3.2
Classifier: Programming Language :: Python :: 3.3
Classifier: Programming Language :: Python :: 3.4
Classifier: Programming Language :: Python :: Implementation :: PyPy
Classifier: Topic :: Software Development :: Libraries :: Python Modules
License-File: LICENSE
License-File: LICENSE.txt
Requires-Dist: requests (>=0.8.8)
